tronalddump/__init__.py
tronalddump/api.py
tronalddump/parse.py
tronald_dumpy-0.1.dist-info/LICENSE
tronald_dumpy-0.1.dist-info/METADATA
tronald_dumpy-0.1.dist-info/WHEEL
tronald_dumpy-0.1.dist-info/top_level.txt
tronald_dumpy-0.1.dist-info/RECORD
