Metadata-Version: 2.1
Name: tronald-dumpy
Version: 0.1
Summary: Python wrapper for the TronaldDump API
Home-page: https://github.com/Gushka/tronalddump-python
Author: gushka
Author-email: guskhka@gmail.com
License: GPLv3
Platform: UNKNOWN
Requires-Python: >=3.6
Requires-Dist: requests
Requires-Dist: urllib3
